dm_cli/__init__.py
dm_cli/dmss.py
dm_cli/domain.py
dm_cli/enums.py
dm_cli/import_entity.py
dm_cli/import_package.py
dm_cli/package_tree_from_zip.py
dm_cli/state.py
dm_cli/command_group/__init__.py
dm_cli/command_group/data_source.py
dm_cli/command_group/entities.py
dm_cli/dmss_api/__init__.py
dm_cli/dmss_api/api_client.py
dm_cli/dmss_api/configuration.py
dm_cli/dmss_api/exceptions.py
dm_cli/dmss_api/model_utils.py
dm_cli/dmss_api/rest.py
dm_cli/dmss_api/api/__init__.py
dm_cli/dmss_api/api/access_control_api.py
dm_cli/dmss_api/api/attribute_api.py
dm_cli/dmss_api/api/blob_api.py
dm_cli/dmss_api/api/blueprint_api.py
dm_cli/dmss_api/api/datasource_api.py
dm_cli/dmss_api/api/default_api.py
dm_cli/dmss_api/api/document_api.py
dm_cli/dmss_api/api/entity_api.py
dm_cli/dmss_api/api/export_api.py
dm_cli/dmss_api/api/file_api.py
dm_cli/dmss_api/api/health_check_api.py
dm_cli/dmss_api/api/lookup_table_api.py
dm_cli/dmss_api/api/meta_api.py
dm_cli/dmss_api/api/personal_access_token_api.py
dm_cli/dmss_api/api/reference_api.py
dm_cli/dmss_api/api/search_api.py
dm_cli/dmss_api/api/whoami_api.py
dm_cli/dmss_api/model/__init__.py
dm_cli/dmss_api/model/access_control_list.py
dm_cli/dmss_api/model/access_level.py
dm_cli/dmss_api/model/acl.py
dm_cli/dmss_api/model/data_source_information.py
dm_cli/dmss_api/model/data_source_request.py
dm_cli/dmss_api/model/dependency.py
dm_cli/dmss_api/model/entity.py
dm_cli/dmss_api/model/error_response.py
dm_cli/dmss_api/model/export_meta_response.py
dm_cli/dmss_api/model/get_blueprint_response.py
dm_cli/dmss_api/model/lookup.py
dm_cli/dmss_api/model/pat_data.py
dm_cli/dmss_api/model/recipe.py
dm_cli/dmss_api/model/recipe_attribute.py
dm_cli/dmss_api/model/reference.py
dm_cli/dmss_api/model/reference_entity.py
dm_cli/dmss_api/model/repository.py
dm_cli/dmss_api/model/repository_type.py
dm_cli/dmss_api/model/storage_attribute.py
dm_cli/dmss_api/model/storage_data_types.py
dm_cli/dmss_api/model/storage_recipe.py
dm_cli/dmss_api/models/__init__.py
dm_cli-1.7.1.dist-info/METADATA
dm_cli-1.7.1.dist-info/WHEEL
dm_cli-1.7.1.dist-info/top_level.txt
dm_cli-1.7.1.dist-info/RECORD
