Metadata-Version: 2.1
Name: dm-cli
Version: 1.7.1
Home-page: https://github.com/equinor/dm-cli
Author: 
Author-email: 
License: MIT
Classifier: Programming Language :: Python :: 3.8
Classifier: Operating System :: OS Independent
Requires-Python: >=3.8
Requires-Dist: requests >=2.31.0
Requires-Dist: emoji >=2.8.0
Requires-Dist: tqdm >=4.66.1
Requires-Dist: frozendict >=2.3.8
Requires-Dist: typing-extensions >=4.7.1
Requires-Dist: typer[all] >=0.9.0
Requires-Dist: python-dateutil >=2.8.2
Requires-Dist: tenacity >=8.2.3
